monk_orm/__init__.py
monk_orm/compiler.py
monk_orm/dialect.py
monk_orm/predicate.py
monk_orm/sa_version.py
monk_orm/compat/__init__.py
monk_orm/compat/api13.py
monk_orm/compat/core10.py
monk_orm/compat/core14.py
monk_orm/compat/core20.py
monk_orm/support/__init__.py
monk_orm/support/pandas.py
monk_orm/support/polyfill.py
monk_orm/support/util.py
monk_orm/type/__init__.py
monk_orm/type/array.py
monk_orm/type/geospatial.py
monk_orm/type/objects.py
monk_orm/type/vector.py
monk_orm-1.0.10.dist-info/METADATA
monk_orm-1.0.10.dist-info/WHEEL
monk_orm-1.0.10.dist-info/top_level.txt
monk_orm-1.0.10.dist-info/RECORD
