Metadata-Version: 2.2
Name: monk-orm
Version: 1.0.10
Summary: An ORM for monkdb based on SQLAlchemy python library
Author-email: MonkDB Devs <devs@atomstate.com>
License: Apache License 2.0
Keywords: MonkDB,monkdb,orm,pg,PostgreSQL,pandas,dask,data,io,sql
Classifier: Development Status :: 5 - Production/Stable
Classifier: Environment :: Plugins
Classifier: Intended Audience :: Customer Service
Classifier: Intended Audience :: Developers
Classifier: Intended Audience :: Education
Classifier: Intended Audience :: End Users/Desktop
Classifier: Intended Audience :: Information Technology
Classifier: Intended Audience :: Manufacturing
Classifier: Intended Audience :: Science/Research
Classifier: Intended Audience :: System Administrators
Classifier: Intended Audience :: Telecommunications Industry
Classifier: License :: OSI Approved :: Apache Software License
Classifier: Operating System :: OS Independent
Classifier: Operating System :: POSIX :: Linux
Classifier: Operating System :: Unix
Classifier: Programming Language :: Python
Classifier: Programming Language :: Python :: 3 :: Only
Classifier: Programming Language :: Python :: 3.6
Classifier: Programming Language :: Python :: 3.7
Classifier: Programming Language :: Python :: 3.8
Classifier: Programming Language :: Python :: 3.9
Classifier: Programming Language :: Python :: 3.10
Classifier: Programming Language :: Python :: 3.11
Classifier: Programming Language :: Python :: 3.12
Classifier: Programming Language :: Python :: 3.13
Classifier: Programming Language :: Python :: Implementation :: CPython
Classifier: Programming Language :: Python :: Implementation :: PyPy
Classifier: Programming Language :: SQL
Classifier: Topic :: Adaptive Technologies
Classifier: Topic :: Communications
Classifier: Topic :: Database
Classifier: Topic :: Documentation
Classifier: Topic :: Education
Classifier: Topic :: Internet
Classifier: Topic :: Office/Business
Classifier: Topic :: Scientific/Engineering
Classifier: Topic :: Software Development :: Libraries
Classifier: Topic :: Software Development :: Pre-processors
Classifier: Topic :: Software Development :: Testing
Classifier: Topic :: Software Development :: Version Control
Classifier: Topic :: System :: Archiving
Classifier: Topic :: System :: Benchmark
Classifier: Topic :: System :: Clustering
Classifier: Topic :: System :: Distributed Computing
Classifier: Topic :: System :: Logging
Classifier: Topic :: System :: Monitoring
Classifier: Topic :: System :: Networking
Classifier: Topic :: System :: Systems Administration
Classifier: Topic :: Text Processing
Classifier: Topic :: Utilities
Requires-Python: >=3.6
Requires-Dist: backports.zoneinfo<1; python_version < "3.9"
Requires-Dist: monkdb==1.0.3
Requires-Dist: geojson<4,>=2.5
Requires-Dist: importlib-metadata; python_version < "3.8"
Requires-Dist: importlib-resources; python_version < "3.9"
Requires-Dist: sqlalchemy<2.1,>=1
Requires-Dist: verlib2<0.4
Requires-Dist: numpy
Provides-Extra: test
Requires-Dist: dask[dataframe]; python_version < "3.13" and extra == "test"
Requires-Dist: pandas<2.3; extra == "test"
Requires-Dist: pytest<9; extra == "test"
Requires-Dist: pytest-cov<7; extra == "test"
Requires-Dist: pytest-mock<4; extra == "test"
Requires-Dist: pueblo; python_version >= "3.7" and extra == "test"
Provides-Extra: develop
Requires-Dist: mypy<1.16; extra == "develop"
Requires-Dist: ruff<0.10; extra == "develop"
Requires-Dist: validate-pyproject<0.24; extra == "develop"
Requires-Dist: pyproject-fmt<2.6; python_version >= "3.9" and extra == "develop"
Requires-Dist: poethepoet<0.33; python_version >= "3.9" and extra == "develop"
Requires-Dist: poethepoet<0.18; python_version < "3.9" and extra == "develop"
Provides-Extra: doc
Requires-Dist: sphinx<9,>=3.5; extra == "doc"
Provides-Extra: release
Requires-Dist: build<2; extra == "release"
Requires-Dist: twine<7; extra == "release"
